LICENSE.txt
README.md
setup.cfg
setup.py
django_azure/__init__.py
django_azure/blob_storage.py
django_azure/event_hubs.py
django_azure/table_storage.py
django_client_db/__init__.py
django_client_db/base_seeder.py
django_client_mail/__init__.py
django_client_mail/email_service.py
django_client_sso/__init__.py
django_client_sso/client_base.py
django_client_sso/client_office365.py
django_client_sso/decorators.py
django_client_sso/exceptions.py
django_client_sso/handlers.py
django_sso_client.egg-info/PKG-INFO
django_sso_client.egg-info/SOURCES.txt
django_sso_client.egg-info/dependency_links.txt
django_sso_client.egg-info/top_level.txt
django_utils/__init__.py
django_utils/local_file.py
django_utils/logger_app.py