Metadata-Version: 2.1
Name: django-sso-client
Version: 0.0.9
Summary: Client for Django Apps - TIT/Hyper by P&D
Home-page: https://TITBrasil@dev.azure.com/TITBrasil/TITCS%20-%20Live4Safe/_git/DJANGO_CLIENT
Author: TIT CS
Author-email: contato@titcs.com.br
License: MIT
Project-URL: Código fonte, https://TITBrasil@dev.azure.com/TITBrasil/Gamefica/_git/DJANGO_CLIENT
Project-URL: Download, https://TITBrasil@dev.azure.com/TITBrasil/Gamefica/_git/DJANGO_CLIENT
Keywords: django_client_sso django_azure django_client_db django_client_mail django_utils
Platform: UNKNOWN
Classifier: Development Status :: 5 - Production/Stable
Classifier: Intended Audience :: Developers
Classifier: License :: OSI Approved :: MIT License
Classifier: Natural Language :: Portuguese (Brazilian)
Classifier: Operating System :: OS Independent
Classifier: Topic :: Software Development :: Internationalization
Classifier: Topic :: Scientific/Engineering :: Physics
License-File: LICENSE.txt
